sttn/__init__.py
sttn/constants.py
sttn/io.py
sttn/network.py
sttn/skeleton.py
sttn/utils.py
sttn/algorithms/__init__.py
sttn/algorithms/community/__init__.py
sttn/algorithms/community/detection.py
sttn/data/__init__.py
sttn/data/brno.py
sttn/data/census.py
sttn/data/data_provider.py
sttn/data/lehd.py
sttn/data/nyc.py
sttn/eval/README.md
sttn/eval/__init__.py
sttn/eval/analyst_eval.ipynb
sttn/eval/dataset.py
sttn/eval/eval_runner.py
sttn/eval/evaluators.py
sttn/nli/__init__.py
sttn/nli/analyst.py
sttn/nli/data.py
sttn/nli/prompts.py
sttn/nli/query.py
sttn/nli/models/__init__.py
sttn/nli/models/output.py
sttn/nli/templates/code_execution_error.j2
sttn/nli/templates/data_analysis.j2
sttn/nli/templates/data_filter.j2
sttn/nli/templates/data_provider.j2
sttn/nli/templates/data_provider_arguments.j2
sttn/plot/__init__.py
sttn/plot/api.py
sttn/plot/keplergl/__init__.py
sttn/plot/keplergl/filter.py
sttn/plot/keplergl/layer.py
sttn/plot/keplergl/map.py
sttn-0.4.0.dist-info/AUTHORS.rst
sttn-0.4.0.dist-info/LICENSE.txt
sttn-0.4.0.dist-info/METADATA
sttn-0.4.0.dist-info/WHEEL
sttn-0.4.0.dist-info/top_level.txt
sttn-0.4.0.dist-info/RECORD
