Metadata-Version: 2.2
Name: sttn
Version: 0.4.0
Summary: Library for spatio-temporal transactional network analysis
Home-page: https://github.com/yuribogomolov/sttn
Author: Yuri Bogomolov
Author-email: bogomoloviura@gmail.com
License: GNU GPLv3
Project-URL: Documentation, https://github.com/yuribogomolov/sttn#readme
Project-URL: Bug Tracker, https://github.com/yuribogomolov/sttn/issues
Platform: any
Classifier: Development Status :: 4 - Beta
Classifier: Programming Language :: Python
License-File: LICENSE.txt
License-File: AUTHORS.rst
Requires-Dist: importlib-metadata; python_version < "3.8"
Requires-Dist: pandas
Requires-Dist: numpy
Requires-Dist: networkx
Requires-Dist: geopandas
Requires-Dist: requests
Requires-Dist: pyarrow
Requires-Dist: scikit-mobility
Requires-Dist: haversine
Provides-Extra: testing
Requires-Dist: pytest; extra == "testing"
Requires-Dist: pytest-cov; extra == "testing"
